netkiller/__init__.py
netkiller_project-0.0.3.dist-info/LICENSE
netkiller_project-0.0.3.dist-info/METADATA
netkiller_project-0.0.3.dist-info/WHEEL
netkiller_project-0.0.3.dist-info/top_level.txt
netkiller_project-0.0.3.dist-info/RECORD
