Metadata-Version: 2.1
Name: netkiller-project
Version: 0.0.3
Summary: Netkiller Python Package
Home-page: https://github.com/netkiller/netkiller.netkiller.io
Author: Neo Chen
Author-email: netkiller@msn.com
License: UNKNOWN
Platform: UNKNOWN
Classifier: Programming Language :: Python :: 3
Classifier: License :: OSI Approved :: MIT License
Classifier: Operating System :: OS Independent
